abracudabra/__init__.py
abracudabra/_annotations.py
abracudabra/_import.py
abracudabra/_validate.py
abracudabra/py.typed
abracudabra/testing.py
abracudabra/conversion/__init__.py
abracudabra/conversion/_cdtype.py
abracudabra/conversion/carray.py
abracudabra/conversion/cframe.py
abracudabra/conversion/ctensor.py
abracudabra/device/__init__.py
abracudabra/device/base.py
abracudabra/device/conversion.py
abracudabra/device/library.py
abracudabra/device/query.py
abracudabra-0.1.3.dist-info/METADATA
abracudabra-0.1.3.dist-info/WHEEL
abracudabra-0.1.3.dist-info/licenses/LICENSE
abracudabra-0.1.3.dist-info/RECORD
